premeidePackageTest/__init__.py
premeidePackageTest/flash.py
premeidePackageTest/test.py
premeidePackageTest/classes/Constants.py
premeidePackageTest/classes/File_gen.py
premeidePackageTest/classes/__init__.py
premeidePackageTest/classes/features/Box.py
premeidePackageTest/classes/features/GradeDistribution.py
premeidePackageTest/classes/features/PBC.py
premeidePackageTest/classes/features/QuestionTable.py
premeidePackageTest/classes/features/QuestionTimeAverage.py
premeidePackageTest/classes/features/TaskDuration.py
premeidePackageTest/classes/features/__init__.py
premeidePackageTest/classes/json/Exam.py
premeidePackageTest/classes/json/Question.py
premeidePackageTest/classes/json/Result.py
premeidePackageTest/classes/json/ResultWrapper.py
premeidePackageTest/classes/json/__init__.py
premeidePackageTest/templates/index.html
premeidePackageTest-0.1.23.dist-info/LICENSE
premeidePackageTest-0.1.23.dist-info/METADATA
premeidePackageTest-0.1.23.dist-info/WHEEL
premeidePackageTest-0.1.23.dist-info/top_level.txt
premeidePackageTest-0.1.23.dist-info/RECORD
