Metadata-Version: 2.1
Name: premeidePackageTest
Version: 0.1.23
Summary: Exam analyzer is a tool that extract data from json files, and the creates visualizations with descriptive texts.
Author: premeide
Author-email: premeide@gmail.com
Keywords: python
Classifier: Development Status :: 1 - Planning
Classifier: Intended Audience :: Developers
Classifier: Programming Language :: Python :: 3
Classifier: Operating System :: Unix
Classifier: Operating System :: MacOS :: MacOS X
Classifier: Operating System :: Microsoft :: Windows
License-File: LICENSE
